dbseeker.py
dbseeker-0.7a0.dist-info/LICENSE
dbseeker-0.7a0.dist-info/METADATA
dbseeker-0.7a0.dist-info/WHEEL
dbseeker-0.7a0.dist-info/top_level.txt
dbseeker-0.7a0.dist-info/RECORD
