Metadata-Version: 2.1
Name: dbseeker
Version: 0.7a0
Summary: A little but functional script that lets you search on every database of a MySQL server for an input string.
Home-page: https://github.com/dueclic/dbseeker
Author: dueclic
Author-email: info@dueclic.com
License: MIT
License-File: LICENSE
Requires-Dist: mysql-connector-python
Requires-Dist: tabulate
